{
  "config": {
    "configFile": "C:\\Users\\Nimrod\\Documents\\javascript\\domain audit\\playwright.config.js",
    "rootDir": "C:/Users/Nimrod/Documents/javascript/domain audit/tests/e2e",
    "forbidOnly": false,
    "fullyParallel": true,
    "globalSetup": null,
    "globalTeardown": null,
    "globalTimeout": 0,
    "grep": {},
    "grepInvert": null,
    "maxFailures": 0,
    "metadata": {
      "actualWorkers": 7
    },
    "preserveOutput": "always",
    "reporter": [
      [
        "html",
        null
      ],
      [
        "json",
        {
          "outputFile": "playwright-report/results.json"
        }
      ],
      [
        "junit",
        {
          "outputFile": "playwright-report/results.xml"
        }
      ]
    ],
    "reportSlowTests": {
      "max": 5,
      "threshold": 300000
    },
    "quiet": false,
    "projects": [
      {
        "outputDir": "C:/Users/Nimrod/Documents/javascript/domain audit/test-results",
        "repeatEach": 1,
        "retries": 0,
        "metadata": {
          "actualWorkers": 7
        },
        "id": "chromium",
        "name": "chromium",
        "testDir": "C:/Users/Nimrod/Documents/javascript/domain audit/tests/e2e",
        "testIgnore": [],
        "testMatch": [
          "**/*.@(spec|test).?(c|m)[jt]s?(x)"
        ],
        "timeout": 30000
      },
      {
        "outputDir": "C:/Users/Nimrod/Documents/javascript/domain audit/test-results",
        "repeatEach": 1,
        "retries": 0,
        "metadata": {
          "actualWorkers": 7
        },
        "id": "firefox",
        "name": "firefox",
        "testDir": "C:/Users/Nimrod/Documents/javascript/domain audit/tests/e2e",
        "testIgnore": [],
        "testMatch": [
          "**/*.@(spec|test).?(c|m)[jt]s?(x)"
        ],
        "timeout": 30000
      },
      {
        "outputDir": "C:/Users/Nimrod/Documents/javascript/domain audit/test-results",
        "repeatEach": 1,
        "retries": 0,
        "metadata": {
          "actualWorkers": 7
        },
        "id": "webkit",
        "name": "webkit",
        "testDir": "C:/Users/Nimrod/Documents/javascript/domain audit/tests/e2e",
        "testIgnore": [],
        "testMatch": [
          "**/*.@(spec|test).?(c|m)[jt]s?(x)"
        ],
        "timeout": 30000
      },
      {
        "outputDir": "C:/Users/Nimrod/Documents/javascript/domain audit/test-results",
        "repeatEach": 1,
        "retries": 0,
        "metadata": {
          "actualWorkers": 7
        },
        "id": "Mobile Chrome",
        "name": "Mobile Chrome",
        "testDir": "C:/Users/Nimrod/Documents/javascript/domain audit/tests/e2e",
        "testIgnore": [],
        "testMatch": [
          "**/*.@(spec|test).?(c|m)[jt]s?(x)"
        ],
        "timeout": 30000
      },
      {
        "outputDir": "C:/Users/Nimrod/Documents/javascript/domain audit/test-results",
        "repeatEach": 1,
        "retries": 0,
        "metadata": {
          "actualWorkers": 7
        },
        "id": "Mobile Safari",
        "name": "Mobile Safari",
        "testDir": "C:/Users/Nimrod/Documents/javascript/domain audit/tests/e2e",
        "testIgnore": [],
        "testMatch": [
          "**/*.@(spec|test).?(c|m)[jt]s?(x)"
        ],
        "timeout": 30000
      }
    ],
    "shard": null,
    "updateSnapshots": "missing",
    "updateSourceMethod": "patch",
    "version": "1.54.2",
    "workers": 8,
    "webServer": null
  },
  "suites": [
    {
      "title": "smoke.spec.js",
      "file": "smoke.spec.js",
      "column": 0,
      "line": 0,
      "specs": [],
      "suites": [
        {
          "title": "E2E Infrastructure Smoke Test",
          "file": "smoke.spec.js",
          "line": 8,
          "column": 6,
          "specs": [
            {
              "title": "should handle static HTML content",
              "ok": true,
              "tags": [],
              "tests": [
                {
                  "timeout": 30000,
                  "annotations": [],
                  "expectedStatus": "passed",
                  "projectId": "chromium",
                  "projectName": "chromium",
                  "results": [
                    {
                      "workerIndex": 0,
                      "parallelIndex": 0,
                      "status": "passed",
                      "duration": 254,
                      "errors": [],
                      "stdout": [],
                      "stderr": [],
                      "retry": 0,
                      "startTime": "2025-08-06T12:25:35.962Z",
                      "annotations": [],
                      "attachments": []
                    }
                  ],
                  "status": "expected"
                }
              ],
              "id": "2c14808d47b386fba9eb-5222350d3a5b67f2ee27",
              "file": "smoke.spec.js",
              "line": 9,
              "column": 3
            },
            {
              "title": "should handle user interactions",
              "ok": true,
              "tags": [],
              "tests": [
                {
                  "timeout": 30000,
                  "annotations": [],
                  "expectedStatus": "passed",
                  "projectId": "chromium",
                  "projectName": "chromium",
                  "results": [
                    {
                      "workerIndex": 1,
                      "parallelIndex": 1,
                      "status": "passed",
                      "duration": 298,
                      "errors": [],
                      "stdout": [],
                      "stderr": [],
                      "retry": 0,
                      "startTime": "2025-08-06T12:25:35.963Z",
                      "annotations": [],
                      "attachments": []
                    }
                  ],
                  "status": "expected"
                }
              ],
              "id": "2c14808d47b386fba9eb-5dae8246259b1bf2eafd",
              "file": "smoke.spec.js",
              "line": 53,
              "column": 3
            },
            {
              "title": "should handle form interactions",
              "ok": true,
              "tags": [],
              "tests": [
                {
                  "timeout": 30000,
                  "annotations": [],
                  "expectedStatus": "passed",
                  "projectId": "chromium",
                  "projectName": "chromium",
                  "results": [
                    {
                      "workerIndex": 2,
                      "parallelIndex": 2,
                      "status": "passed",
                      "duration": 326,
                      "errors": [],
                      "stdout": [],
                      "stderr": [],
                      "retry": 0,
                      "startTime": "2025-08-06T12:25:35.979Z",
                      "annotations": [],
                      "attachments": []
                    }
                  ],
                  "status": "expected"
                }
              ],
              "id": "2c14808d47b386fba9eb-0713def31fb60d14600e",
              "file": "smoke.spec.js",
              "line": 77,
              "column": 3
            },
            {
              "title": "should capture basic performance metrics",
              "ok": true,
              "tags": [],
              "tests": [
                {
                  "timeout": 30000,
                  "annotations": [],
                  "expectedStatus": "passed",
                  "projectId": "chromium",
                  "projectName": "chromium",
                  "results": [
                    {
                      "workerIndex": 3,
                      "parallelIndex": 3,
                      "status": "passed",
                      "duration": 284,
                      "errors": [],
                      "stdout": [],
                      "stderr": [],
                      "retry": 0,
                      "startTime": "2025-08-06T12:25:35.962Z",
                      "annotations": [],
                      "attachments": []
                    }
                  ],
                  "status": "expected"
                }
              ],
              "id": "2c14808d47b386fba9eb-2411d24d053da4897b5c",
              "file": "smoke.spec.js",
              "line": 112,
              "column": 3
            },
            {
              "title": "should work across different viewports",
              "ok": true,
              "tags": [],
              "tests": [
                {
                  "timeout": 30000,
                  "annotations": [],
                  "expectedStatus": "passed",
                  "projectId": "chromium",
                  "projectName": "chromium",
                  "results": [
                    {
                      "workerIndex": 4,
                      "parallelIndex": 4,
                      "status": "passed",
                      "duration": 328,
                      "errors": [],
                      "stdout": [],
                      "stderr": [],
                      "retry": 0,
                      "startTime": "2025-08-06T12:25:35.963Z",
                      "annotations": [],
                      "attachments": []
                    }
                  ],
                  "status": "expected"
                }
              ],
              "id": "2c14808d47b386fba9eb-ca8e959761fbf6ae7d11",
              "file": "smoke.spec.js",
              "line": 139,
              "column": 3
            },
            {
              "title": "should handle JavaScript execution",
              "ok": true,
              "tags": [],
              "tests": [
                {
                  "timeout": 30000,
                  "annotations": [],
                  "expectedStatus": "passed",
                  "projectId": "chromium",
                  "projectName": "chromium",
                  "results": [
                    {
                      "workerIndex": 5,
                      "parallelIndex": 5,
                      "status": "passed",
                      "duration": 360,
                      "errors": [],
                      "stdout": [],
                      "stderr": [],
                      "retry": 0,
                      "startTime": "2025-08-06T12:25:35.963Z",
                      "annotations": [],
                      "attachments": []
                    }
                  ],
                  "status": "expected"
                }
              ],
              "id": "2c14808d47b386fba9eb-76bad1d6b232572c2052",
              "file": "smoke.spec.js",
              "line": 178,
              "column": 3
            },
            {
              "title": "should verify browser capabilities",
              "ok": true,
              "tags": [],
              "tests": [
                {
                  "timeout": 30000,
                  "annotations": [],
                  "expectedStatus": "passed",
                  "projectId": "chromium",
                  "projectName": "chromium",
                  "results": [
                    {
                      "workerIndex": 6,
                      "parallelIndex": 6,
                      "status": "passed",
                      "duration": 283,
                      "errors": [],
                      "stdout": [
                        {
                          "text": "Testing on chromium\n"
                        }
                      ],
                      "stderr": [],
                      "retry": 0,
                      "startTime": "2025-08-06T12:25:35.978Z",
                      "annotations": [],
                      "attachments": []
                    }
                  ],
                  "status": "expected"
                }
              ],
              "id": "2c14808d47b386fba9eb-9a765bb51f6f5082ef8b",
              "file": "smoke.spec.js",
              "line": 200,
              "column": 3
            }
          ]
        }
      ]
    }
  ],
  "errors": [],
  "stats": {
    "startTime": "2025-08-06T12:25:35.237Z",
    "duration": 1216.875,
    "expected": 7,
    "skipped": 0,
    "unexpected": 0,
    "flaky": 0
  }
}